{
    "category-poa": {
        "geometry": "point",
        "name": "Point of alert",
        "members": [
            "poa/post_wegoto",
            "poa/streetlamp_wegoto",
            "poa/roadsign_wegoto",
            "poa/trash_wegoto",
            "poa/billboard_wegoto",
            "poa/morriscolumn_wegoto",
            "poa/byciclepark_wegoto",
            "poa/coverstop_wegoto",
            "poa/notcoverstop_wegoto",
            "poa/bench_wegoto",
            "poa/gardenerbox_wegoto",
            "poa/masterpiece_wegoto",
            "poa/electricalpanel_wegoto",
            "poa/parkingmeter_wegoto",
            "poa/metalgate_wegoto",
            "poa/overhanging_wegoto",
            "poa/tree_wegoto",
            "poa/rail_wegoto",
            "poa/benchstand_wegoto",
            "poa/letterbox_wegoto",
            "poa/toilet_wegoto",
            "poa/handicapparking_wegoto",
            "poa/atm_wegoto",
            "poa/separatewaste_wegoto",
            "poa/constrastedsign_wegoto",
            "poa/bicycle_wegoto",
            "poa/conservatory_wegoto",
            "poa/carpool_wegoto",
            "poa/electricCharge_wegoto",
            "poa/fall_wegoto",
            "poa/crack_wegoto",
            "poa/frontstep_wegoto"
        ]
    },
    "category-poi": {
        "geometry": "point",
        "name": "Point of interest",
        "icon": "marker",
        "members": [
            "poi/atm_wegoto",
            "poi/bicycle_wegoto",
            "poi/carpool_wegoto",
            "poi/coverstop_wegoto",
            "poi/gardenerbox_wegoto",
            "poi/handicapparking_wegoto",
            "poi/letterbox_wegoto",
            "poi/masterpiece_wegoto",
            "poi/notcoverstop_wegoto",
            "poi/parkingmeter_wegoto",
            "poi/separatewaste_wegoto",
            "poi/toilet_wegoto"
        ]
    },
    "category-road": {
        "geometry": "line",
        "name": "Road Features",
        "icon": "category-roads",
        "members": [
            "highway/trottoir_wegoto",
            "highway/chemin_wegoto",
            "highway/chausse_wegoto",
            "highway/pietonne_wegoto",
            "highway/cyclable_wegoto",
            "highway/traversee_wegoto",
            "highway/ilot_wegoto",
            "highway/autre_wegoto"
        ]
    }
}